LICENSE
MANIFEST.in
README.md
VERSION
requirements.txt
setup.py
texta_crf_extractor/__init__.py
texta_crf_extractor/config.py
texta_crf_extractor/crf_extractor.py
texta_crf_extractor/exceptions.py
texta_crf_extractor/feature_extraction.py
texta_crf_extractor/tagging_report.py
texta_crf_extractor.egg-info/PKG-INFO
texta_crf_extractor.egg-info/SOURCES.txt
texta_crf_extractor.egg-info/dependency_links.txt
texta_crf_extractor.egg-info/requires.txt
texta_crf_extractor.egg-info/top_level.txt