Metadata-Version: 2.1
Name: texta-crf-extractor
Version: 2.1.1
Summary: texta-crf-extractor
Home-page: https://git.texta.ee/texta/texta-crf-extractor-python
Author: TEXTA
Author-email: info@texta.ee
License: GPLv3
Platform: UNKNOWN
Provides-Extra: mlp
License-File: LICENSE
